pytest_skip_slow.py
pytest_skip_slow-0.0.3.dist-info/entry_points.txt
pytest_skip_slow-0.0.3.dist-info/LICENSE
pytest_skip_slow-0.0.3.dist-info/WHEEL
pytest_skip_slow-0.0.3.dist-info/METADATA
pytest_skip_slow-0.0.3.dist-info/RECORD
