Metadata-Version: 2.1
Name: pytest-skip-slow
Version: 0.0.3
Summary: A pytest plugin to skip `@pytest.mark.slow` tests by default. 
Author-email: Brian Okken <brian+pypi@pythontest.com>
Requires-Python: >=3.7
Classifier: License :: OSI Approved :: MIT License
Classifier: Framework :: Pytest
Requires-Dist: pytest>=6.2.0
Requires-Dist: tox ; extra == "test"
Project-URL: Home, https://github.com/okken/pytest-skip-slow
Provides-Extra: test
